{
	"version": "https://jsonfeed.org/version/1",
	"title": "Adam Procter",
	"home_page_url": "http://discursive.adamprocter.co.uk/",
	"feed_url": "http://discursive.adamprocter.co.uk/feed.json",
	"items": [
		
		{
			"id": "http://adamprocter.micro.blog/2017/09/26/bluegrass-jamming.html",
	      	
			"content_html": "<p>Bluegrass jamming 👍😊</p>\n\n<p><img src=\"http://discursive.adamprocter.co.uk/uploads/2017/cc82cad96c.jpg\" width=\"600\" height=\"600\" /></p>\n",
			"date_published": "2017-09-26T21:32:00+01:00",
			"url": "http://discursive.adamprocter.co.uk/2017/09/26/bluegrass-jamming.html"
		},
		
		{
			"id": "http://adamprocter.micro.blog/2017/09/26/rsadesign-ideo-designthinking.html",
	      	
			"content_html": "<h1 id=\"rsadesign-ideo-designthinking-ideasofrevolt-humanitycentred\">rsadesign #ideo #designthinking #ideasofrevolt #humanitycentred</h1>\n\n<p><img src=\"http://discursive.adamprocter.co.uk/uploads/2017/0698935ea7.jpg\" width=\"600\" height=\"547\" /></p>\n",
			"date_published": "2017-09-26T20:20:00+01:00",
			"url": "http://discursive.adamprocter.co.uk/2017/09/26/rsadesign-ideo-designthinking.html"
		},
		
		{
			"id": "http://adamprocter.micro.blog/2017/09/26/please-excuse-some.html",
	      	
			"content_html": "<p>Please excuse some of the janky formatting on twitter all my posts now come via Micro.blog best place to read my short stuff is at <a href=\"http://discursive.adamprocter.co.uk\">discursive.adamprocter.co.uk</a> 🦄</p>\n",
			"date_published": "2017-09-26T19:27:00+01:00",
			"url": "http://discursive.adamprocter.co.uk/2017/09/26/please-excuse-some.html"
		},
		
		{
			"id": "http://adamprocter.micro.blog/2017/09/26/the-copenhagen-letter.html",
	      	
			"content_html": "<h1 id=\"the-copenhagen-letter-2017\">THE COPENHAGEN LETTER 2017</h1>\n<p>Let us move from human-centered design to humanity-centered design.</p>\n\n<ul>\n  <li><a href=\"http://dctr.pro/20u\">dctr.pro/20u</a></li>\n</ul>\n",
			"date_published": "2017-09-26T19:14:00+01:00",
			"url": "http://discursive.adamprocter.co.uk/2017/09/26/the-copenhagen-letter.html"
		},
		
		{
			"id": "http://adamprocter.micro.blog/2017/09/26/power-of-design.html",
	      	
			"content_html": "<h1 id=\"power-of-design-thinking\">Power of Design Thinking</h1>\n\n<ul>\n  <li>Ask Human Centred Questions</li>\n  <li>Create Movements not Mandates</li>\n  <li>Be Optimistic </li>\n</ul>\n\n<p>Sue Siddall #rsadesign</p>\n",
			"date_published": "2017-09-26T19:07:00+01:00",
			"url": "http://discursive.adamprocter.co.uk/2017/09/26/power-of-design.html"
		},
		
		{
			"id": "http://adamprocter.micro.blog/2017/09/26/new-screen-in.html",
	      	
			"content_html": "<p>New screen in our @gamesdesignart studio 16 is coming in useful - 4K (Games) Design Thinking #rsadesign</p>\n\n<p><img src=\"http://discursive.adamprocter.co.uk/uploads/2017/e856e1f3a8.jpg\" width=\"600\" height=\"600\" /></p>\n",
			"date_published": "2017-09-26T18:32:00+01:00",
			"url": "http://discursive.adamprocter.co.uk/2017/09/26/new-screen-in.html"
		},
		
		{
			"id": "http://adamprocter.micro.blog/2017/09/26/oh-my-word.html",
	      	
			"content_html": "<p>Oh my word Firefox Quantum is FAST! Its here now in Beta &amp; Developer Edition - The Mozilla Blog - <a href=\"http://dctr.pro/20t\">dctr.pro/20t</a></p>\n",
			"date_published": "2017-09-26T18:19:00+01:00",
			"url": "http://discursive.adamprocter.co.uk/2017/09/26/oh-my-word.html"
		},
		
		{
			"id": "http://adamprocter.micro.blog/2017/09/26/easily-print-github.html",
	      	
			"content_html": "<p>Easily print GitHub markdown as beautiful PDFs <a href=\"http://dctr.pro/20s\">dctr.pro/20s</a></p>\n",
			"date_published": "2017-09-26T16:37:00+01:00",
			"url": "http://discursive.adamprocter.co.uk/2017/09/26/easily-print-github.html"
		},
		
		{
			"id": "http://adamprocter.micro.blog/2017/09/26/ultimate-iphone-size.html",
	      	
			"content_html": "<p>Ultimate iPhone size guide from Paintcode - <a href=\"http://dctr.pro/20r\">dctr.pro/20r</a></p>\n",
			"date_published": "2017-09-26T09:04:00+01:00",
			"url": "http://discursive.adamprocter.co.uk/2017/09/26/ultimate-iphone-size.html"
		},
		
		{
			"id": "http://adamprocter.micro.blog/2017/09/25/great-insight-into.html",
	      	
			"content_html": "<p>Great insight into the work Garnet Hetrz has been doing talk today @winchesterart #designedu</p>\n\n<p><img src=\"http://discursive.adamprocter.co.uk/uploads/2017/1ee147626f.jpg\" width=\"600\" height=\"600\" /></p>\n",
			"date_published": "2017-09-25T21:53:00+01:00",
			"url": "http://discursive.adamprocter.co.uk/2017/09/25/great-insight-into.html"
		}
		
	]
}
