{
	"version": "https://jsonfeed.org/version/1",
	"title": "Adam Procter",
	"home_page_url": "https://discursive.adamprocter.co.uk/",
	"feed_url": "https://discursive.adamprocter.co.uk/feed.json",
	"items": [
		
		{
			"id": "http://adamprocter.micro.blog/2018/04/21/a-space-odyssey.html",
	      	
			"content_html": "<p>2001: A Space Odyssey”: What It Means, and How It Was Made</p>\n\n<ul>\n  <li><a href=\"http://dctr.pro/263\">dctr.pro/263</a></li>\n</ul>\n",
			"date_published": "2018-04-21T20:24:07+01:00",
			"url": "https://discursive.adamprocter.co.uk/2018/04/21/a-space-odyssey.html"
		},
		
		{
			"id": "http://adamprocter.micro.blog/2018/04/21/incoming-storm.html",
	      	
			"content_html": "<p>Incoming storm ⛈ 🌩</p>\n",
			"date_published": "2018-04-21T20:21:24+01:00",
			"url": "https://discursive.adamprocter.co.uk/2018/04/21/incoming-storm.html"
		},
		
		{
			"id": "http://adamprocter.micro.blog/2018/04/21/oldham-game.html",
	      	
			"title": "Oldham game ",
			
			"content_html": "<p>Pre Game</p>\n\n<p><a href=\"http://discursive.adamprocter.co.uk/uploads/2018/fae571ec15.jpg\"><img src=\"http://discursive.adamprocter.co.uk/uploads/2018/fae571ec15.jpg\" width=\"450\" height=\"600\" style=\"display: inline-block; max-height: 200px; width: auto; padding: 1px;\" class=\"sunlit_image\" /></a><a href=\"http://discursive.adamprocter.co.uk/uploads/2018/a3127352bc.jpg\"><img src=\"http://discursive.adamprocter.co.uk/uploads/2018/a3127352bc.jpg\" width=\"450\" height=\"600\" style=\"display: inline-block; max-height: 200px; width: auto; padding: 1px;\" class=\"sunlit_image\" /></a><a href=\"http://discursive.adamprocter.co.uk/uploads/2018/da0e66f02f.jpg\"><img src=\"http://discursive.adamprocter.co.uk/uploads/2018/da0e66f02f.jpg\" width=\"600\" height=\"450\" style=\"display: inline-block; max-height: 200px; width: auto; padding: 1px;\" class=\"sunlit_image\" /></a><a href=\"http://discursive.adamprocter.co.uk/uploads/2018/c95f4fa11e.jpg\"><img src=\"http://discursive.adamprocter.co.uk/uploads/2018/c95f4fa11e.jpg\" width=\"600\" height=\"450\" style=\"display: inline-block; max-height: 200px; width: auto; padding: 1px;\" class=\"sunlit_image\" /></a></p>\n\n<p>Pretty busy today.  2-2 frustrating but fair result. It’s going to be close</p>\n\n<p>Table As It Stands</p>\n\n<p><a href=\"http://discursive.adamprocter.co.uk/uploads/2018/732e5eecf7.jpg\"><img src=\"http://discursive.adamprocter.co.uk/uploads/2018/732e5eecf7.jpg\" width=\"600\" height=\"556\" style=\"display: inline-block; max-height: 200px; width: auto; padding: 1px;\" class=\"sunlit_image\" /></a></p>\n\n",
			"date_published": "2018-04-21T20:21:03+01:00",
			"url": "https://discursive.adamprocter.co.uk/2018/04/21/oldham-game.html"
		},
		
		{
			"id": "http://adamprocter.micro.blog/2018/04/21/time-flies-ev.html",
	      	
			"content_html": "<p>Time flies. EV at retro vintage day out.</p>\n\n<p><img src=\"http://discursive.adamprocter.co.uk/uploads/2018/c104a25b85.jpg\" width=\"600\" height=\"446\" /></p>\n",
			"date_published": "2018-04-21T10:47:39+01:00",
			"url": "https://discursive.adamprocter.co.uk/2018/04/21/time-flies-ev.html"
		},
		
		{
			"id": "http://adamprocter.micro.blog/2018/04/21/tools-and-spaces.html",
	      	
			"content_html": "<table>\n  <tbody>\n    <tr>\n      <td>Tools and spaces to create a positive architecture of participation</td>\n      <td>Open Educational Thinkering</td>\n    </tr>\n  </tbody>\n</table>\n\n<ul>\n  <li><a href=\"http://dctr.pro/25z\">dctr.pro/25z</a></li>\n</ul>\n",
			"date_published": "2018-04-21T09:30:39+01:00",
			"url": "https://discursive.adamprocter.co.uk/2018/04/21/tools-and-spaces.html"
		},
		
		{
			"id": "http://adamprocter.micro.blog/2018/04/21/why-decentralization-matters.html",
	      	
			"content_html": "<p>Why Decentralization Matters – Chris Dixon – Medium</p>\n\n<ul>\n  <li><a href=\"http://dctr.pro/25x\">dctr.pro/25x</a></li>\n</ul>\n",
			"date_published": "2018-04-21T09:29:46+01:00",
			"url": "https://discursive.adamprocter.co.uk/2018/04/21/why-decentralization-matters.html"
		},
		
		{
			"id": "http://adamprocter.micro.blog/2018/04/21/tosdr-the-wikipedia.html",
	      	
			"content_html": "<p>ToSDR the Wikipedia of terms and services. Helping you navigate the insane terms on many websites.</p>\n\n<ul>\n  <li><a href=\"http://dctr.pro/25w\">dctr.pro/25w</a></li>\n</ul>\n",
			"date_published": "2018-04-21T09:18:54+01:00",
			"url": "https://discursive.adamprocter.co.uk/2018/04/21/tosdr-the-wikipedia.html"
		},
		
		{
			"id": "http://adamprocter.micro.blog/2018/04/21/scientists-accidentally-create.html",
	      	
			"content_html": "<table>\n  <tbody>\n    <tr>\n      <td>Scientists accidentally create mutant enzyme that eats plastic bottles</td>\n      <td>Environment</td>\n      <td>The Guardian.</td>\n    </tr>\n  </tbody>\n</table>\n\n<ul>\n  <li><a href=\"http://dctr.pro/25v\">dctr.pro/25v</a></li>\n</ul>\n",
			"date_published": "2018-04-21T09:15:08+01:00",
			"url": "https://discursive.adamprocter.co.uk/2018/04/21/scientists-accidentally-create.html"
		},
		
		{
			"id": "http://adamprocter.micro.blog/2018/04/20/the-declutter-experimentwhat.html",
	      	
			"content_html": "<h1 id=\"the-declutter-experiment\">The Declutter Experiment.</h1>\n<p>What happened when 1600+  participants take a break from “optional technologies” including most notably social media for a month - <a href=\"http://dctr.pro/262\">dctr.pro/262</a></p>\n",
			"date_published": "2018-04-20T20:27:50+01:00",
			"url": "https://discursive.adamprocter.co.uk/2018/04/20/the-declutter-experimentwhat.html"
		},
		
		{
			"id": "http://adamprocter.micro.blog/2018/04/20/sleepover-with-a.html",
	      	
			"content_html": "<p>Sleepover with a difference.</p>\n\n<p><img src=\"http://discursive.adamprocter.co.uk/uploads/2018/e05e409a54.jpg\" width=\"600\" height=\"450\" /></p>\n",
			"date_published": "2018-04-20T20:19:39+01:00",
			"url": "https://discursive.adamprocter.co.uk/2018/04/20/sleepover-with-a.html"
		},
		
		{
			"id": "http://adamprocter.micro.blog/2018/04/20/done-it-phew.html",
	      	
			"content_html": "<p>Done it, phew. Weekend starts here.</p>\n<blockquote>\n  <p>Thank you for your submitted application for the 2018-2019 Mozilla Fellowship cohort!</p>\n</blockquote>\n\n<blockquote>\n  <p>We will deliberate in the weeks following our application close-date, April 20th, and contact applicants before the end of May 2018.</p>\n</blockquote>\n",
			"date_published": "2018-04-20T18:41:23+01:00",
			"url": "https://discursive.adamprocter.co.uk/2018/04/20/done-it-phew.html"
		},
		
		{
			"id": "http://adamprocter.micro.blog/2018/04/20/163645.html",
	      	
			"content_html": "<p>The Woman Who Gave the Macintosh a Smile | The New Yorker - <a href=\"http://dctr.pro/261\">dctr.pro/261</a></p>\n<blockquote>\n  <p>Kare, who is sixty-four, will be honoured for her work on April 20th, by her fellow designers, with the prestigious AIGA medal.</p>\n</blockquote>\n\n<p><img src=\"http://discursive.adamprocter.co.uk/uploads/2018/3f5907e582.jpg\" width=\"436\" height=\"600\" /></p>\n",
			"date_published": "2018-04-20T17:36:45+01:00",
			"url": "https://discursive.adamprocter.co.uk/2018/04/20/163645.html"
		},
		
		{
			"id": "http://adamprocter.micro.blog/2018/04/20/rise-of-the.html",
	      	
			"content_html": "<p>Rise of the T Skill Designer - Marvel Blog <a href=\"http://dctr.pro/260\">dctr.pro/260</a></p>\n",
			"date_published": "2018-04-20T17:29:20+01:00",
			"url": "https://discursive.adamprocter.co.uk/2018/04/20/rise-of-the.html"
		},
		
		{
			"id": "http://adamprocter.micro.blog/2018/04/20/research-groups-i.html",
	      	
			"content_html": "<p>Research groups I have an active connection with:</p>\n\n<ul>\n  <li><a href=\"https://www.southampton.ac.uk/wsi\">www.southampton.ac.uk/wsi</a></li>\n  <li><a href=\"http://futureoftext.org/future-of-text.html\">futureoftext.org/future-of…</a></li>\n  <li><a href=\"https://www.ecs.soton.ac.uk/research/wais\">www.ecs.soton.ac.uk/research/…</a></li>\n  <li><a href=\"https://www.southampton.ac.uk/amt\">www.southampton.ac.uk/amt</a></li>\n  <li><a href=\"https://www.southampton.ac.uk/cpwsa/\">www.southampton.ac.uk/cpwsa/</a></li>\n</ul>\n",
			"date_published": "2018-04-20T17:20:19+01:00",
			"url": "https://discursive.adamprocter.co.uk/2018/04/20/research-groups-i.html"
		},
		
		{
			"id": "http://adamprocter.micro.blog/2018/04/19/091013.html",
	      	
			"content_html": "<p><img src=\"http://discursive.adamprocter.co.uk/uploads/2018/17c2005fe1.jpg\" width=\"600\" height=\"600\" /></p>\n",
			"date_published": "2018-04-19T10:10:13+01:00",
			"url": "https://discursive.adamprocter.co.uk/2018/04/19/091013.html"
		},
		
		{
			"id": "http://adamprocter.micro.blog/2018/04/18/sketches-from-china.html",
	      	
			"title": "Sketches From China",
			
			"content_html": "<p><a href=\"http://discursive.adamprocter.co.uk/uploads/2018/7a6fc36dbd.jpg\"><img src=\"http://discursive.adamprocter.co.uk/uploads/2018/7a6fc36dbd.jpg\" width=\"600\" height=\"450\" style=\"display: inline-block; max-height: 200px; width: auto; padding: 1px;\" class=\"sunlit_image\" /></a><a href=\"http://discursive.adamprocter.co.uk/uploads/2018/b9d61d4a0b.jpg\"><img src=\"http://discursive.adamprocter.co.uk/uploads/2018/b9d61d4a0b.jpg\" width=\"450\" height=\"600\" style=\"display: inline-block; max-height: 200px; width: auto; padding: 1px;\" class=\"sunlit_image\" /></a><a href=\"http://discursive.adamprocter.co.uk/uploads/2018/3ef4ea63d6.jpg\"><img src=\"http://discursive.adamprocter.co.uk/uploads/2018/3ef4ea63d6.jpg\" width=\"600\" height=\"450\" style=\"display: inline-block; max-height: 200px; width: auto; padding: 1px;\" class=\"sunlit_image\" /></a></p>\n\n<p>Colleague Daniel Hobson gave me awesome set of his sketches from recent trip to China. Super chuffed, I really like them.</p>\n\n",
			"date_published": "2018-04-18T22:32:46+01:00",
			"url": "https://discursive.adamprocter.co.uk/2018/04/18/sketches-from-china.html"
		},
		
		{
			"id": "http://adamprocter.micro.blog/2018/04/18/mini-golf-event.html",
	      	
			"title": "Mini golf Event WSA 2018",
			
			"content_html": "<p><a href=\"http://discursive.adamprocter.co.uk/uploads/2018/bf9e7fd3ca.jpg\"><img src=\"http://discursive.adamprocter.co.uk/uploads/2018/bf9e7fd3ca.jpg\" width=\"450\" height=\"600\" style=\"display: inline-block; max-height: 200px; width: auto; padding: 1px;\" class=\"sunlit_image\" /></a><a href=\"http://discursive.adamprocter.co.uk/uploads/2018/e7228ff7bb.jpg\"><img src=\"http://discursive.adamprocter.co.uk/uploads/2018/e7228ff7bb.jpg\" width=\"450\" height=\"600\" style=\"display: inline-block; max-height: 200px; width: auto; padding: 1px;\" class=\"sunlit_image\" /></a><a href=\"http://discursive.adamprocter.co.uk/uploads/2018/2c25800545.jpg\"><img src=\"http://discursive.adamprocter.co.uk/uploads/2018/2c25800545.jpg\" width=\"450\" height=\"600\" style=\"display: inline-block; max-height: 200px; width: auto; padding: 1px;\" class=\"sunlit_image\" /></a><a href=\"http://discursive.adamprocter.co.uk/uploads/2018/324d35e232.jpg\"><img src=\"http://discursive.adamprocter.co.uk/uploads/2018/324d35e232.jpg\" width=\"450\" height=\"600\" style=\"display: inline-block; max-height: 200px; width: auto; padding: 1px;\" class=\"sunlit_image\" /></a><a href=\"http://discursive.adamprocter.co.uk/uploads/2018/8b7ad5eb43.jpg\"><img src=\"http://discursive.adamprocter.co.uk/uploads/2018/8b7ad5eb43.jpg\" width=\"450\" height=\"600\" style=\"display: inline-block; max-height: 200px; width: auto; padding: 1px;\" class=\"sunlit_image\" /></a><a href=\"http://discursive.adamprocter.co.uk/uploads/2018/83257da43b.jpg\"><img src=\"http://discursive.adamprocter.co.uk/uploads/2018/83257da43b.jpg\" width=\"450\" height=\"600\" style=\"display: inline-block; max-height: 200px; width: auto; padding: 1px;\" class=\"sunlit_image\" /></a><a href=\"http://discursive.adamprocter.co.uk/uploads/2018/dcded06679.jpg\"><img src=\"http://discursive.adamprocter.co.uk/uploads/2018/dcded06679.jpg\" width=\"450\" height=\"600\" style=\"display: inline-block; max-height: 200px; width: auto; padding: 1px;\" class=\"sunlit_image\" /></a><a href=\"http://discursive.adamprocter.co.uk/uploads/2018/9fb460382b.jpg\"><img src=\"http://discursive.adamprocter.co.uk/uploads/2018/9fb460382b.jpg\" width=\"600\" height=\"450\" style=\"display: inline-block; max-height: 200px; width: auto; padding: 1px;\" class=\"sunlit_image\" /></a><a href=\"http://discursive.adamprocter.co.uk/uploads/2018/16ccc8ef15.jpg\"><img src=\"http://discursive.adamprocter.co.uk/uploads/2018/16ccc8ef15.jpg\" width=\"450\" height=\"600\" style=\"display: inline-block; max-height: 200px; width: auto; padding: 1px;\" class=\"sunlit_image\" /></a><a href=\"http://discursive.adamprocter.co.uk/uploads/2018/3fd04e550c.jpg\"><img src=\"http://discursive.adamprocter.co.uk/uploads/2018/3fd04e550c.jpg\" width=\"600\" height=\"450\" style=\"display: inline-block; max-height: 200px; width: auto; padding: 1px;\" class=\"sunlit_image\" /></a></p>\n\n<p>Postponed mini golf event for Games Design students on a perfect weather day ☀️ fun fair themed course.</p>\n\n",
			"date_published": "2018-04-18T22:01:45+01:00",
			"url": "https://discursive.adamprocter.co.uk/2018/04/18/mini-golf-event.html"
		},
		
		{
			"id": "http://adamprocter.micro.blog/2018/04/17/filming-workshop-with.html",
	      	
			"content_html": "<p>Filming workshop with @mindthefilm and Games students. 2018 #WSAxARCADE interview footage day.</p>\n\n<p><img src=\"http://discursive.adamprocter.co.uk/uploads/2018/8824e126e2.jpg\" width=\"600\" height=\"357\" /><img src=\"http://discursive.adamprocter.co.uk/uploads/2018/fd616a2292.jpg\" width=\"600\" height=\"347\" /><img src=\"http://discursive.adamprocter.co.uk/uploads/2018/ac4708e4fa.jpg\" width=\"600\" height=\"320\" /><img src=\"http://discursive.adamprocter.co.uk/uploads/2018/6d03ef86e8.jpg\" width=\"600\" height=\"385\" /><img src=\"http://discursive.adamprocter.co.uk/uploads/2018/f3856d13aa.jpg\" width=\"600\" height=\"339\" /></p>\n",
			"date_published": "2018-04-17T21:29:51+01:00",
			"url": "https://discursive.adamprocter.co.uk/2018/04/17/filming-workshop-with.html"
		},
		
		{
			"id": "http://adamprocter.micro.blog/2018/04/17/vimeo-and-youtube.html",
	      	
			"content_html": "<p>Vimeo and Youtube LIKEs hooked into my micro.blog timeline. Good times indeed.</p>\n",
			"date_published": "2018-04-17T21:04:35+01:00",
			"url": "https://discursive.adamprocter.co.uk/2018/04/17/vimeo-and-youtube.html"
		},
		
		{
			"id": "http://adamprocter.micro.blog/2018/04/17/intimate-data-analytics.html",
	      	
			"content_html": "<h1 id=\"intimate-data-analytics-in-education\">Intimate data analytics in education</h1>\n\n<p>Excellent <a href=\"http://dctr.pro/25t\">overview</a> from <a href=\"https://micro.blog/thoughtshrapnel\">@thoughtshrapnel</a></p>\n\n<blockquote>\n  <p>If the advocates of ‘precision education’  have their way, I wonder who will actually create something meaningful that opposes their technocratic worldview?</p>\n</blockquote>\n\n<p>gonna try #procterphd</p>\n",
			"date_published": "2018-04-17T20:50:08+01:00",
			"url": "https://discursive.adamprocter.co.uk/2018/04/17/intimate-data-analytics.html"
		},
		
		{
			"id": "http://adamprocter.micro.blog/2018/04/17/just-grabbed-brentsimmons.html",
	      	
			"content_html": "<p>Just grabbed @brentsimmon’s Evergreen rss reader. Nice way to collect my lists of links from RSS feeds via share to email option. And it seems a really snappy app as well. I’d love a date range pref. Perhaps thats for version 2.0 😊</p>\n",
			"date_published": "2018-04-17T13:35:15+01:00",
			"url": "https://discursive.adamprocter.co.uk/2018/04/17/just-grabbed-brentsimmons.html"
		},
		
		{
			"id": "http://adamprocter.micro.blog/2018/04/17/a-couple-of.html",
	      	
			"content_html": "<p>A couple of hours into Zuckerberg at congress. Interesting although to be fair nothing new in terms of understanding facebooks data gathering buisness model. Fair play for Zuckerberg to stand by what his company does but clearly unethical at the core.</p>\n\n<p><img src=\"http://discursive.adamprocter.co.uk/uploads/2018/6195e5f975.jpg\" width=\"600\" height=\"600\" /></p>\n",
			"date_published": "2018-04-17T01:05:31+01:00",
			"url": "https://discursive.adamprocter.co.uk/2018/04/17/a-couple-of.html"
		},
		
		{
			"id": "http://adamprocter.micro.blog/2018/04/16/193542.html",
	      	
			"content_html": "<p>In case you missed it on Sunday here is the link to the last 7 of the last 7 <a href=\"http://adamprocter.co.uk/sendy/w/mXt8V9ZSIgPScCu76372wAnA\">14-04-18</a></p>\n",
			"date_published": "2018-04-16T20:35:42+01:00",
			"url": "https://discursive.adamprocter.co.uk/2018/04/16/193542.html"
		},
		
		{
			"id": "http://adamprocter.micro.blog/2018/04/16/180149.html",
	      	
			"content_html": "<p>Awesome gift from awesome friend, a flat dotted grid sketchbook. This will be deployed for #procterphd for sure!</p>\n\n<p><img src=\"http://discursive.adamprocter.co.uk/uploads/2018/758fa0e5da.jpg\" width=\"600\" height=\"450\" /><img src=\"http://discursive.adamprocter.co.uk/uploads/2018/0775d107b7.jpg\" width=\"450\" height=\"600\" /></p>\n",
			"date_published": "2018-04-16T19:01:49+01:00",
			"url": "https://discursive.adamprocter.co.uk/2018/04/16/180149.html"
		},
		
		{
			"id": "http://adamprocter.micro.blog/2018/04/15/glitch-video-intros.html",
	      	
			"content_html": "<p>Glitch video intros to HTML CSS JavaScript and Node. <a href=\"http://dctr.pro/25q\">dctr.pro/25q</a> #learningtocode</p>\n",
			"date_published": "2018-04-15T21:17:24+01:00",
			"url": "https://discursive.adamprocter.co.uk/2018/04/15/glitch-video-intros.html"
		}
		
	]
}
